w_pgs/__cls_pgs_conn__.py
w_pgs/__init__.py
w_pgs-1.3.dist-info/LICENSE
w_pgs-1.3.dist-info/METADATA
w_pgs-1.3.dist-info/WHEEL
w_pgs-1.3.dist-info/top_level.txt
w_pgs-1.3.dist-info/RECORD
