Metadata-Version: 2.1
Name: w-pgs
Version: 1.3
Summary: A useless database connection based on psycopg2
Home-page: https://github.com/zzt/w-rst.git
Author: zzt
Author-email: zzt@qq.com
License: MIT
Keywords: wpgs
License-File: LICENSE
Requires-Dist: datetime
